rest_framework_multi_models/__init__.py
rest_framework_multi_models/generics.py
rest_framework_multi_models/mixins.py
rest_framework_multi_models/pagination.py
rest_framework_multi_models/utils/__init__.py
rest_framework_multi_models/utils/comparables.py
rest_framework_multi_models/utils/types.py
rest_framework_multi_models/views.py
rest_framework_multi_models/viewset.py
djangorestframework_multimodels-0.0.2.dist-info/LICENSE
djangorestframework_multimodels-0.0.2.dist-info/METADATA
djangorestframework_multimodels-0.0.2.dist-info/WHEEL
djangorestframework_multimodels-0.0.2.dist-info/RECORD
