Metadata-Version: 2.3
Name: djangorestframework-multimodels
Version: 0.0.2
Summary: 
License: The MIT License (MIT)
Keywords: Django,Django Rest Framework,DRF,MultiModel,Multiple Models
Author: Gonzalo Molpeceres Barrientos
Author-email: gonzalomolbar@gmail.com
Requires-Python: >=3.12
Classifier: Development Status :: 4 - Beta
Classifier: Framework :: Django
Classifier: Intended Audience :: Developers
Classifier: License :: Other/Proprietary License
Classifier: Operating System :: OS Independent
Classifier: Programming Language :: Python :: 3
Classifier: Programming Language :: Python :: 3.12
Classifier: Programming Language :: Python :: 3.13
Requires-Dist: django (>=4,<6)
Requires-Dist: djangorestframework (>=3.15,<4)
Project-URL: Repository, https://github.com/gonzalomolbar/django-rest-framework-multi-models
